odoo/addons/project_hr/README.rst
odoo/addons/project_hr/__init__.py
odoo/addons/project_hr/__manifest__.py
odoo/addons/project_hr/i18n/de.po
odoo/addons/project_hr/i18n/es.po
odoo/addons/project_hr/i18n/project_hr.pot
odoo/addons/project_hr/i18n/sl.po
odoo/addons/project_hr/models/__init__.py
odoo/addons/project_hr/models/hr_employee.py
odoo/addons/project_hr/models/project_project.py
odoo/addons/project_hr/models/project_task.py
odoo/addons/project_hr/models/res_users.py
odoo/addons/project_hr/readme/CONFIGURE.rst
odoo/addons/project_hr/readme/CONTRIBUTORS.rst
odoo/addons/project_hr/readme/DESCRIPTION.rst
odoo/addons/project_hr/readme/ROADMAP.rst
odoo/addons/project_hr/readme/USAGE.rst
odoo/addons/project_hr/static/description/icon.png
odoo/addons/project_hr/static/description/index.html
odoo/addons/project_hr/tests/__init__.py
odoo/addons/project_hr/tests/test_project_hr.py
odoo/addons/project_hr/views/project_project_views.xml
odoo/addons/project_hr/views/project_task_views.xml
odoo12_addon_project_hr-12.0.1.0.1.dist-info/METADATA
odoo12_addon_project_hr-12.0.1.0.1.dist-info/WHEEL
odoo12_addon_project_hr-12.0.1.0.1.dist-info/top_level.txt
odoo12_addon_project_hr-12.0.1.0.1.dist-info/RECORD
