Metadata-Version: 2.1
Name: odoo12-addon-project-hr
Version: 12.0.1.0.1
Summary: Link HR with project
Home-page: https://github.com/OCA/project
Author: Tecnativa,Odoo Community Association (OCA)
Author-email: support@odoo-community.org
License: AGPL-3
Platform: UNKNOWN
Classifier: Programming Language :: Python
Classifier: Framework :: Odoo
Classifier: License :: OSI Approved :: GNU Affero General Public License v3
Classifier: Development Status :: 5 - Production/Stable
Requires-Python: >=3.5
Requires-Dist: odoo (<12.1dev,>=12.0a)
